radiometer_api/__init__.py
radiometer_api/radiometer_api.py
radiometerAPI-1.0.8.dist-info/METADATA
radiometerAPI-1.0.8.dist-info/WHEEL
radiometerAPI-1.0.8.dist-info/top_level.txt
radiometerAPI-1.0.8.dist-info/RECORD
