Metadata-Version: 2.1
Name: radiometerAPI
Version: 1.0.8
Summary: API for radiometer
Home-page: http://www.example.com/
Author: aburgart02
Author-email: 
License: UNKNOWN
Project-URL: Documentation, https://github.com/aburgart02/radiometer-api
Project-URL: Source Code, https://github.com/aburgart02/radiometer-api
Project-URL: Bug Tracker, https://github.com/aburgart02/radiometer-api
Keywords: radiometer
Platform: UNKNOWN
Classifier: Programming Language :: Python :: 3.10
Requires-Python: >=3.10
Requires-Dist: requests (>=2.27.1)
Requires-Dist: aiohttp (>=3.9.2)
